<adtree>
  <node refinement="conjunctive">
    <label>AND_1</label>
    <node switchRole="yes" refinement="conjunctive">
      <label>AND_2</label>
      <node refinement="">
        <label>BS_3</label>
        <parameter domainId="MinCost1" category="basic">82476</parameter>
      </node>
      <node switchRole="yes" refinement="">
        <label>BS_4</label>
        <parameter domainId="MinCost1" category="basic">10530</parameter>
      </node>
    </node>
    <node refinement="">
      <label>BS_5</label>
      <parameter domainId="MinCost1" category="basic">57530</parameter>
    </node>
    <node refinement="">
      <label>BS_6</label>
      <parameter domainId="MinCost1" category="basic">5278</parameter>
    </node>
    <node refinement="disjunctive">
      <label>OR_7</label>
      <node refinement="conjunctive">
        <label>AND_8</label>
        <node switchRole="yes" refinement="conjunctive">
          <label>AND_9</label>
          <node refinement="">
            <label>BS_10</label>
            <parameter domainId="MinCost1" category="basic">6533</parameter>
          </node>
          <node refinement="">
            <label>BS_11</label>
            <parameter domainId="MinCost1" category="basic">16713</parameter>
          </node>
        </node>
        <node refinement="disjunctive">
          <label>OR_12</label>
          <node refinement="">
            <label>BS_13</label>
            <parameter domainId="MinCost1" category="basic">54184</parameter>
          </node>
          <node switchRole="yes" refinement="">
            <label>BS_14</label>
            <parameter domainId="MinCost1" category="basic">27778</parameter>
          </node>
        </node>
        <node refinement="">
          <label>BS_15</label>
          <parameter domainId="MinCost1" category="basic">72699</parameter>
        </node>
      </node>
      <node refinement="">
        <label>BS_16</label>
        <parameter domainId="MinCost1" category="basic">12836</parameter>
      </node>
    </node>
  </node>
  <domain id="MinCost1">
    <class>lu.uni.adtool.domains.adtpredefined.MinCost</class>
    <tool>ADTool2</tool>
  </domain>
</adtree>