<adtree>
  <node refinement="conjunctive">
    <label>OR1</label>
    <node refinement="conjunctive">
      <label>a2</label>
      <parameter domainId="MinCost1" category="basic">76407</parameter>
      <node refinement="conjunctive" switchRole="yes">
        <label>AND1</label>
        <node refinement="conjunctive">
          <label>UqW4v5C8gU</label>
          <node refinement="conjunctive">
            <label>qDiXb1OqfE</label>
            <parameter domainId="MinCost1" category="basic">79480</parameter>
            <node refinement="conjunctive" switchRole="yes">
              <label>pdLW4oaiWS</label>
              <node refinement="conjunctive">
                <label>Yb1VYPEf6g</label>
                <parameter domainId="MinCost1" category="basic">80264</parameter>
              </node>
              <node refinement="conjunctive">
                <label>9W8B2I0FyV</label>
                <node refinement="conjunctive">
                  <label>IQp5utInZD</label>
                  <parameter domainId="MinCost1" category="basic">95328</parameter>
                  <node refinement="conjunctive" switchRole="yes">
                    <label>LKe9i2b5cZ</label>
                    <node refinement="conjunctive">
                      <label>0u0Tq3VKTp</label>
                      <node refinement="conjunctive">
                        <label>6Zujvm9fRA</label>
                        <parameter domainId="MinCost1" category="basic">44141</parameter>
                        <node refinement="conjunctive" switchRole="yes">
                          <label>AehDaGFXj1</label>
                          <node refinement="conjunctive">
                            <label>kM50ARM40b</label>
                            <parameter domainId="MinCost1" category="basic">76640</parameter>
                          </node>
                          <node refinement="conjunctive">
                            <label>yWzex7k8dR</label>
                            <parameter domainId="MinCost1" category="basic">67971</parameter>
                          </node>
                          <node refinement="conjunctive" switchRole="yes">
                            <label>PVZ0xyBR5H</label>
                            <parameter domainId="MinCost1" category="basic">15443</parameter>
                          </node>
                        </node>
                      </node>
                      <node refinement="conjunctive">
                        <label>MQIoEi933r</label>
                        <parameter domainId="MinCost1" category="basic">36124</parameter>
                      </node>
                    </node>
                    <node refinement="conjunctive">
                      <label>siFfvxjvx8</label>
                      <node refinement="conjunctive">
                        <label>L4Zo9ujDkc</label>
                        <parameter domainId="MinCost1" category="basic">39390</parameter>
                        <node refinement="conjunctive" switchRole="yes">
                          <label>CAmyAylw9a</label>
                          <node refinement="conjunctive">
                            <label>A4Wb2LH2Gi</label>
                            <parameter domainId="MinCost1" category="basic">6507</parameter>
                          </node>
                          <node refinement="conjunctive">
                            <label>FvXwyzzsED</label>
                            <node refinement="conjunctive">
                              <label>Phh7IbIJ8F</label>
                              <parameter domainId="MinCost1" category="basic">7538</parameter>
                              <node refinement="conjunctive" switchRole="yes">
                                <label>5ODJ91ZZBo</label>
                                <node refinement="conjunctive">
                                  <label>XNoxqNLmAt</label>
                                  <parameter domainId="MinCost1" category="basic">39013</parameter>
                                </node>
                                <node refinement="conjunctive">
                                  <label>q1rarbcQ4b</label>
                                  <parameter domainId="MinCost1" category="basic">23323</parameter>
                                </node>
                                <node refinement="conjunctive" switchRole="yes">
                                  <label>sKr69zookB</label>
                                  <parameter domainId="MinCost1" category="basic">83968</parameter>
                                </node>
                              </node>
                            </node>
                            <node refinement="conjunctive">
                              <label>3NecnpqyzA</label>
                              <parameter domainId="MinCost1" category="basic">45842</parameter>
                            </node>
                          </node>
                          <node refinement="conjunctive" switchRole="yes">
                            <label>EaSIFuLBMP</label>
                            <parameter domainId="MinCost1" category="basic">20904</parameter>
                          </node>
                        </node>
                      </node>
                      <node refinement="conjunctive">
                        <label>DA4FLIDk1O</label>
                        <parameter domainId="MinCost1" category="basic">40814</parameter>
                      </node>
                    </node>
                    <node refinement="conjunctive" switchRole="yes">
                      <label>CL9Rhod1qL</label>
                      <parameter domainId="MinCost1" category="basic">70154</parameter>
                    </node>
                  </node>
                </node>
                <node refinement="conjunctive">
                  <label>phISuxD6sw</label>
                  <parameter domainId="MinCost1" category="basic">85367</parameter>
                </node>
              </node>
              <node refinement="conjunctive" switchRole="yes">
                <label>GKJ9h3loEi</label>
                <parameter domainId="MinCost1" category="basic">33174</parameter>
              </node>
            </node>
          </node>
          <node refinement="conjunctive">
            <label>2hC3A6hbJH</label>
            <parameter domainId="MinCost1" category="basic">32813</parameter>
          </node>
        </node>
        <node refinement="conjunctive">
          <label>d2</label>
          <parameter domainId="MinCost1" category="basic">12567</parameter>
        </node>
        <node refinement="conjunctive" switchRole="yes">
          <label>a1</label>
          <parameter domainId="MinCost1" category="basic">5294</parameter>
        </node>
      </node>
    </node>
    <node refinement="conjunctive">
      <label>a3</label>
      <parameter domainId="MinCost1" category="basic">9230</parameter>
    </node>
  </node>
  <domain id="MinCost1">
    <class>lu.uni.adtool.domains.adtpredefined.MinCost</class>
    <tool>ADTool2</tool>
  </domain>
</adtree>